timeseries_feature_engineering/__init__.py
timeseries_feature_engineering/_nbdev.py
timeseries_feature_engineering/core.py
timeseries_feature_engineering-0.0.1.dist-info/LICENSE
timeseries_feature_engineering-0.0.1.dist-info/METADATA
timeseries_feature_engineering-0.0.1.dist-info/WHEEL
timeseries_feature_engineering-0.0.1.dist-info/entry_points.txt
timeseries_feature_engineering-0.0.1.dist-info/top_level.txt
timeseries_feature_engineering-0.0.1.dist-info/RECORD
