Metadata-Version: 2.1
Name: timeseries-feature-engineering
Version: 0.0.1
Summary: A description of your project
Home-page: https://github.com/shanaka-desoysa/timeseries_feature_engineering/tree/master/
Author: Shanka DeSoysa
Author-email: shanaka@computer.org
License: Apache Software License 2.0
Keywords: some keywords
Platform: UNKNOWN
Classifier: Development Status :: 3 - Alpha
Classifier: Intended Audience :: Developers
Classifier: License :: OSI Approved :: Apache Software License
Classifier: Natural Language :: English
Classifier: Programming Language :: Python :: 3.6
Classifier: Programming Language :: Python :: 3.7
Classifier: Programming Language :: Python :: 3.8
Requires-Python: >=3.6
Requires-Dist: fastcore
Requires-Dist: pandas
